Metadata-Version: 2.1
Name: django-je
Version: 0.0.1
Summary: This is a simple library that performs a colect packages of django and more.
Home-page: https://github.com/
Author: JAMAL EL KHDADI
Author-email: jamalelkhdadi@gmail.com
License: MIT
Keywords: cli
Classifier: Development Status :: 5 - Production/Stable
Classifier: Intended Audience :: Developers
Classifier: Intended Audience :: Science/Research
Classifier: Intended Audience :: Education
Classifier: Natural Language :: English
Classifier: Operating System :: Microsoft :: Windows :: Windows 10
Classifier: License :: OSI Approved :: MIT License
Classifier: Programming Language :: Python :: 3.6
Classifier: Programming Language :: Python :: 3.7
Classifier: Programming Language :: Python :: 3.8
Classifier: Programming Language :: Python :: 3.9
Classifier: Programming Language :: Python :: 3.10
License-File: LICENSE
